proxy_randomizer/__init__.py
proxy_randomizer/cli.py
proxy_randomizer/providers.py
proxy_randomizer/proxy.py
proxy_randomizer/utils.py
proxy_randomizer-1.3.5.dist-info/AUTHORS.rst
proxy_randomizer-1.3.5.dist-info/LICENSE
proxy_randomizer-1.3.5.dist-info/METADATA
proxy_randomizer-1.3.5.dist-info/WHEEL
proxy_randomizer-1.3.5.dist-info/entry_points.txt
proxy_randomizer-1.3.5.dist-info/top_level.txt
proxy_randomizer-1.3.5.dist-info/RECORD
