Metadata-Version: 1.2
Name: proxy-randomizer
Version: 1.3.5
Summary: proxy randomizer
Home-page: https://github.com/esequiel378/proxy_randomizer
Author: Esequiel Albornoz
Author-email: esequielalbornoz7@gmail.com
License: MIT license
Keywords: proxy_randomizer
Platform: UNKNOWN
Classifier: Development Status :: 2 - Pre-Alpha
Classifier: Intended Audience :: Developers
Classifier: License :: OSI Approved :: MIT License
Classifier: Natural Language :: English
Classifier: Programming Language :: Python :: 3.6
Classifier: Programming Language :: Python :: 3.7
Classifier: Programming Language :: Python :: 3.8
Classifier: Programming Language :: Python :: 3.9
Requires-Python: >=3.6
